cbc_api/__init__.py
cbc_api/__main__.py
cbc_api/app.py
cbc_api/config.json
cbc_api/config_manager.py
cbc_api/geo/__init__.py
cbc_api/geo/msdn.py
cbc_api/schedule/__init__.py
cbc_api/schedule/schedule.py
cbc_api/schedule/tsp.py
cbc_api-0.1.0.dist-info/DESCRIPTION.rst
cbc_api-0.1.0.dist-info/METADATA
cbc_api-0.1.0.dist-info/RECORD
cbc_api-0.1.0.dist-info/WHEEL
cbc_api-0.1.0.dist-info/entry_points.txt
cbc_api-0.1.0.dist-info/metadata.json
cbc_api-0.1.0.dist-info/top_level.txt
