Metadata-Version: 2.0
Name: cbc-api
Version: 0.1.0
Summary: API for the CBC app
Home-page: UNKNOWN
Author: CBC Datakind Team
Author-email: UNKNOWN
License: UNKNOWN
Platform: UNKNOWN
Requires-Dist: click
Requires-Dist: daiquiri
Requires-Dist: eventlet
Requires-Dist: flask
Requires-Dist: flask-socketio
Requires-Dist: googlemaps
Requires-Dist: pytest
Requires-Dist: numpy
Requires-Dist: scipy
Requires-Dist: sklearn
Requires-Dist: shapely
Requires-Dist: pyschedule (>=0.2.16)
